Metadata-Version: 2.1
Name: chatget
Version: 1.5
Summary: A simple library that allows the user to very easily grab the contents of a Twitch chat!
Home-page: https://github.com/aidan-octane/chatget
Download-URL: https://github.com/aidan-octane/chatGET/archive/refs/tags/v1.5.tar.gz
Author: tachophobicat
Author-email: tachophobicat@gmail.com
License: MIT
Keywords: Twitch,chat,get,easy,simple
Classifier: Development Status :: 3 - Alpha
Classifier: Intended Audience :: Developers
Classifier: Topic :: Software Development :: Build Tools
Classifier: License :: OSI Approved :: MIT License
Classifier: Programming Language :: Python :: 3
Classifier: Programming Language :: Python :: 3.4
Classifier: Programming Language :: Python :: 3.5
Classifier: Programming Language :: Python :: 3.6
License-File: LICENSE.txt
